{"project_info":{"project_id":"pledge-flask-44ac0","project_number":"819783267264","name":"pledge-flask"},"client":[{"client_info":{"mobilesdk_app_id":"1:819783267264:android:09affbcbc6f3d64c","client_id":"android:com.pledgeapp.pledge","client_type":1,"android_client_info":{"package_name":"com.pledgeapp.pledge"}},"oauth_client":[{"client_id":"819783267264-b645ojb5agefe5qaupmbaoaklahueb2h.apps.googleusercontent.com","client_type":1,"android_info":{"package_name":"com.pledgeapp.pledge","certificate_hash":"16d637df53a481b518daad07b99233083836fd0f"}}],"api_key":[],"services":{"analytics_service":{"status":1},"cloud_messaging_service":{"status":1,"apns_config":[]},"appinvite_service":{"status":1,"other_platform_oauth_client":[]},"google_signin_service":{"status":2},"ads_service":{"status":1}}}],"client_info":[],"ARTIFACT_VERSION":"1"}